finance_mauritius/__init__.py
finance_mauritius/mcb.py
finance_mauritius/sbm.py
finance_mauritius-0.2.0.dist-info/METADATA
finance_mauritius-0.2.0.dist-info/WHEEL
finance_mauritius-0.2.0.dist-info/RECORD
