Metadata-Version: 2.3
Name: finance-mauritius
Version: 0.2.0
Summary: Useful functions for Mauritius banks and financials institutions like MRA (Mauritius Revenue Authority)
Project-URL: Homepage, https://github.com/abdur-rahmaanJ/finance-mauritius
Project-URL: Documentation, https://github.com/abdur-rahmaanJ/finance-mauritius
Project-URL: Repository, https://github.com/abdur-rahmaanJ/finance-mauritius.git
Project-URL: Bug Tracker, https://github.com/abdur-rahmaanJ/finance-mauritius/issues
Project-URL: Changelog, https://github.com/abdur-rahmaanJ/finance-mauritius/blob/stable/CHANGELOG.md
Author-email: Abdur-RahmaanJ <arj.python@gmail.com>
Keywords: mauritius,mcb,sbm
Requires-Python: >=3.8
Requires-Dist: polars>=0.20.17
